{
  "SavedData": [
    {
      "id": 118,
      "Heading": "TOP NEWS",
      "description": "The iPhone 14 Max will support Face ID and will rely on the A15 Bionic that TSMC will continue to build on 5 nm nodes.",
      "title": "Apple iPhone 14 Max specifications revealed months ahead of launch - BGR India",
      "urlToImage": "https://st1.bgr.in/wp-content/uploads/2022/04/apple-iPhone-14-1-.jpg",
      "publishedAt": "2022-05-07T04:06:00Z"
    },
    {
      "id": 116,
      "Heading": "TOP NEWS",
      "description": "As Lock Upp grand finale is soon to roll, we contested a poll asking fans who should be the winner among Munawar Faruqui, Prince Narula, Payal Rohatgi and Anjali Arora. The results will shock you.",
      "title": "Lock Upp Winner: Munawar Faruqui BEATS Prince Narula, Payal Rohatgi and others with unimaginable numbers of v - Bollywood Life",
      "urlToImage": "https://st1.bollywoodlife.com/wp-content/uploads/2022/05/Munawar-5-600x315.png",
      "publishedAt": "2022-05-07T04:18:31Z"
    },
    {
      "id": 102,
      "Heading": "TOP NEWS",
      "description": "The government will raise Rs 21,000 crore by issuing 22.13 crore equity shares to the public via initial public offering which will be closed on May 9.",
      "title": "LIC IPO: Issue subscribed 1.79 times on Day 5, policyholders portion booked 5.04 times, retail 1.59 times,... - Moneycontrol",
      "urlToImage": "https://images.moneycontrol.com/static-mcnews/2022/05/LIC-IPO-3-770x433.jpg",
      "publishedAt": "2022-05-08T13:34:05Z"
    }
  ],
  "History": [
    
  ]
}